virne/__init__.py
virne/config.py
virne/base/__init__.py
virne/base/controller.py
virne/base/counter.py
virne/base/environment.py
virne/base/recorder.py
virne/base/scenario.py
virne/base/solution.py
virne/data/__init__.py
virne/data/attribute.py
virne/data/generator.py
virne/data/network.py
virne/data/physical_network.py
virne/data/virtual_network.py
virne/data/virtual_network_request_simulator.py
virne/settings/p_net_setting.yaml
virne/settings/v_sim_setting multi_resource.yaml
virne/settings/v_sim_setting single_resource.yaml
virne/settings/v_sim_setting.yaml
virne/solver/__init__.py
virne/solver/registry.py
virne/solver/solver.py
virne/solver/exact/__init__.py
virne/solver/exact/d_rounding.py
virne/solver/exact/mip.py
virne/solver/exact/r_rounding.py
virne/solver/heuristic/__init__.py
virne/solver/heuristic/bfs_trials.py
virne/solver/heuristic/ego_network.py
virne/solver/heuristic/fit.py
virne/solver/heuristic/joint_pr.py
virne/solver/heuristic/node_rank.py
virne/solver/learning/__init__.py
virne/solver/learning/obs_handler.py
virne/solver/learning/utils.py
virne/solver/learning/a3c_gcn_seq2seq/__init__.py
virne/solver/learning/a3c_gcn_seq2seq/instance_env.py
virne/solver/learning/a3c_gcn_seq2seq/net.py
virne/solver/learning/a3c_gcn_seq2seq/solver.py
virne/solver/learning/ddpg_attention/__init__.py
virne/solver/learning/ddpg_attention/instance_env.py
virne/solver/learning/ddpg_attention/net.py
virne/solver/learning/ddpg_attention/solver.py
virne/solver/learning/gae_clustering/__init__.py
virne/solver/learning/gae_clustering/auto_encoder.py
virne/solver/learning/gae_clustering/gae_clustering.py
virne/solver/learning/gae_clustering/model.py
virne/solver/learning/hopfield_network/__init__.py
virne/solver/learning/hopfield_network/hopfield_network.py
virne/solver/learning/hopfield_network/hopfield_network_solver.py
virne/solver/learning/mcts/__init__.py
virne/solver/learning/mcts/mcts.py
virne/solver/learning/mcts/node.py
virne-0.5.0.dist-info/LICENSE
virne-0.5.0.dist-info/METADATA
virne-0.5.0.dist-info/WHEEL
virne-0.5.0.dist-info/top_level.txt
virne-0.5.0.dist-info/RECORD
