Metadata-Version: 2.1
Name: virne
Version: 0.5.0
Summary: A unified framework for virtual network embedding.
Author-email: GeminiLight <wtfly2018@gmail.com>
License: Apache License, Version 2.0
Project-URL: Homepage, https://github.com/GeminiLight/virne
Project-URL: Repository, https://github.com/GeminiLight/virne
Project-URL: Documentation, https://virne.readthedocs.io
Project-URL: Bug Report, https://github.com/GeminiLight/virne/issues
Keywords: Network Virtualization,Virtual Network Embedding,Reinforcement Learning
Classifier: Development Status :: 4 - Beta
Classifier: License :: OSI Approved :: Apache Software License
Classifier: Programming Language :: Python :: 3
Classifier: Programming Language :: Python :: 3.8
Classifier: Programming Language :: Python :: 3.9
Classifier: Programming Language :: Python :: 3.10
Classifier: Programming Language :: Python :: 3.11
Classifier: Intended Audience :: Science/Research
Classifier: Topic :: Scientific/Engineering :: Artificial Intelligence
Classifier: Topic :: Software Development :: Libraries :: Python Modules
Requires-Python: >=3.8
License-File: LICENSE
Requires-Dist: gym ==0.22.0
Requires-Dist: torch >=1.10.0
Requires-Dist: numpy >=1.20.0
Requires-Dist: pyyaml >=6.0
Requires-Dist: seaborn >=0.12.2
Requires-Dist: pandas >=1.5.3
Requires-Dist: matplotlib >=3.7.1
Requires-Dist: scipy >=1.9.0
Requires-Dist: tensorboard >=2.8.0
Requires-Dist: torch-geometric >=2.0.0
Requires-Dist: higher >=0.2.1
Requires-Dist: networkx >=2.6.0
Requires-Dist: tqdm >=4.62.0
Requires-Dist: ortools >=9.1.9490
Provides-Extra: lint
